DangwomenSihouLinghunQunale/README.md
DangwomenSihouLinghunQunale/__init__.py
DangwomenSihouLinghunQunale/__main__.py
DangwomenSihouLinghunQunale/file.epub
DangwomenSihouLinghunQunale/index.html
DangwomenSihouLinghunQunale/css/__init__.py
DangwomenSihouLinghunQunale/css/annotations.css
DangwomenSihouLinghunQunale/css/main.css
DangwomenSihouLinghunQunale/css/normalize.css
DangwomenSihouLinghunQunale/css/popup.css
DangwomenSihouLinghunQunale/font/__init__.py
DangwomenSihouLinghunQunale/font/fontello.eot
DangwomenSihouLinghunQunale/font/fontello.svg
DangwomenSihouLinghunQunale/font/fontello.ttf
DangwomenSihouLinghunQunale/font/fontello.woff
DangwomenSihouLinghunQunale/img/__init__.py
DangwomenSihouLinghunQunale/img/annotator-glyph-sprite.png
DangwomenSihouLinghunQunale/img/annotator-icon-sprite.png
DangwomenSihouLinghunQunale/img/apple-touch-icon.png
DangwomenSihouLinghunQunale/img/cancelfullscreen.png
DangwomenSihouLinghunQunale/img/close.png
DangwomenSihouLinghunQunale/img/fullscreen.png
DangwomenSihouLinghunQunale/img/loader.gif
DangwomenSihouLinghunQunale/img/menu-icon.png
DangwomenSihouLinghunQunale/img/save.png
DangwomenSihouLinghunQunale/img/saved.png
DangwomenSihouLinghunQunale/img/settings-s.png
DangwomenSihouLinghunQunale/img/settings.png
DangwomenSihouLinghunQunale/img/star.png
DangwomenSihouLinghunQunale/js/__init__.py
DangwomenSihouLinghunQunale/js/epub.js
DangwomenSihouLinghunQunale/js/epub.min.js
DangwomenSihouLinghunQunale/js/epub.min.map
DangwomenSihouLinghunQunale/js/hooks.min.js
DangwomenSihouLinghunQunale/js/hooks.min.map
DangwomenSihouLinghunQunale/js/reader.js
DangwomenSihouLinghunQunale/js/reader.js.map
DangwomenSihouLinghunQunale/js/reader.min.js
DangwomenSihouLinghunQunale/js/reader.min.map
DangwomenSihouLinghunQunale/js/hooks/__init__.py
DangwomenSihouLinghunQunale/js/hooks/extensions/__init__.py
DangwomenSihouLinghunQunale/js/hooks/extensions/highlight.js
DangwomenSihouLinghunQunale/js/libs/__init__.py
dangwomen_sihou_linghun_qunale-2022.10.3.0.dist-info/METADATA
dangwomen_sihou_linghun_qunale-2022.10.3.0.dist-info/WHEEL
dangwomen_sihou_linghun_qunale-2022.10.3.0.dist-info/entry_points.txt
dangwomen_sihou_linghun_qunale-2022.10.3.0.dist-info/top_level.txt
dangwomen_sihou_linghun_qunale-2022.10.3.0.dist-info/RECORD
